acre_api/__init__.py
acre_api/api/__init__.py
acre_api/api/authentication_api.py
acre_api/api/case_api.py
acre_api/api/client_api.py
acre_api/api/commission_structure_api.py
acre_api/api/document_api.py
acre_api/api/document_requirement_api.py
acre_api/api/general_insurance_product_api.py
acre_api/api/group_api.py
acre_api/api/internal_api.py
acre_api/api/mortgage_mortgage_product_api.py
acre_api/api/mortgage_sourcing_api.py
acre_api/api/note_api.py
acre_api/api/organisation_api.py
acre_api/api/permission_api.py
acre_api/api/property_api.py
acre_api/api/protection_product0_api.py
acre_api/api/protection_product_api.py
acre_api/api/role_api.py
acre_api/api/service_api.py
acre_api/api/template_api.py
acre_api/api/user_api.py
acre_api/api_client.py
acre_api/api_response.py
acre_api/configuration.py
acre_api/exceptions.py
acre_api/models/__init__.py
acre_api/models/acre_processor_add_case_protection_product_body.py
acre_api/models/acre_processor_add_general_insurance_product_case_body.py
acre_api/models/acre_processor_create_client_organisation_relationship_body.py
acre_api/models/acre_processor_update_case_status_body.py
acre_api/models/additional_loan_purpose.py
acre_api/models/arrear_creditor_type.py
acre_api/models/authentication_provider_authentication_mechanism.py
acre_api/models/case_details_cancellation_reason.py
acre_api/models/case_details_client_id_and_version.py
acre_api/models/case_details_conveyancer.py
acre_api/models/case_details_conveyancing_status_type.py
acre_api/models/case_details_conveyancing_type.py
acre_api/models/case_details_conveyancing_update.py
acre_api/models/case_details_conveyancing_update_message_type.py
acre_api/models/case_details_conveyancing_update_property.py
acre_api/models/case_details_conveyancing_update_source.py
acre_api/models/case_details_eidv_result_override.py
acre_api/models/case_details_enbs_event.py
acre_api/models/case_details_lead_metadata.py
acre_api/models/case_details_mortgage_reason.py
acre_api-1.2.3.dist-info/METADATA
acre_api-1.2.3.dist-info/WHEEL
acre_api-1.2.3.dist-info/RECORD
